LayerAkira/__init__.py
LayerAkira/executables/__init__.py
LayerAkira/executables/run_cli_client.py
LayerAkira/src/AkiraExchangeClient.py
LayerAkira/src/AkiraFormatter.py
LayerAkira/src/CLIClient.py
LayerAkira/src/ERC20Client.py
LayerAkira/src/HttpClient.py
LayerAkira/src/JointHttpClient.py
LayerAkira/src/OrderSerializer.py
LayerAkira/src/WsClient.py
LayerAkira/src/__init__.py
LayerAkira/src/abi.py
LayerAkira/src/common/ContractAddress.py
LayerAkira/src/common/ERC20Token.py
LayerAkira/src/common/FeeTypes.py
LayerAkira/src/common/Requests.py
LayerAkira/src/common/Responses.py
LayerAkira/src/common/StarknetEntities.py
LayerAkira/src/common/TradedPair.py
LayerAkira/src/common/__init__.py
LayerAkira/src/common/common.py
LayerAkira/src/common/constants.py
LayerAkira/src/hasher/Hasher.py
LayerAkira/src/hasher/__init__.py
LayerAkira/src/hasher/types.py
LayerAkira/src/hasher/utils.py
LayerAkiraSDK-1.0.0a2.dist-info/LICENSE
LayerAkiraSDK-1.0.0a2.dist-info/METADATA
LayerAkiraSDK-1.0.0a2.dist-info/WHEEL
LayerAkiraSDK-1.0.0a2.dist-info/top_level.txt
LayerAkiraSDK-1.0.0a2.dist-info/RECORD
