Metadata-Version: 2.1
Name: LayerAkiraSDK
Version: 1.0.0a2
Summary: library for interaction with LayerAkira exchange
Home-page: https://github.com/LayerAkira/python_akira
Author: Garrancha
License: MIT
Classifier: Intended Audience :: Developers
Classifier: License :: OSI Approved :: MIT License
Classifier: Programming Language :: Python
Classifier: Programming Language :: Python :: 3
Classifier: Programming Language :: Python :: 3.6
Classifier: Programming Language :: Python :: 3.7
Classifier: Programming Language :: Python :: 3.8
Classifier: Programming Language :: Python :: 3.9
Classifier: Programming Language :: Python :: 3.10
Classifier: Programming Language :: Python :: 3.11
Classifier: Programming Language :: Python :: 3.12
Classifier: Operating System :: OS Independent
License-File: LICENSE
Requires-Dist: websockets
Requires-Dist: toml
Requires-Dist: starknet-py >=0.22.0
Requires-Dist: requests
Requires-Dist: aioconsole >=0.7.0
